README.md
setup.py
google_ads_house_keeper.egg-info/PKG-INFO
google_ads_house_keeper.egg-info/SOURCES.txt
google_ads_house_keeper.egg-info/dependency_links.txt
google_ads_house_keeper.egg-info/requires.txt
google_ads_house_keeper.egg-info/top_level.txt
googleads_housekeeper/__init__.py
googleads_housekeeper/bootstrap.py
googleads_housekeeper/views.py
googleads_housekeeper/adapters/__init__.py
googleads_housekeeper/adapters/notifications.py
googleads_housekeeper/adapters/orm.py
googleads_housekeeper/adapters/publisher.py
googleads_housekeeper/adapters/repository.py
googleads_housekeeper/domain/__init__.py
googleads_housekeeper/domain/allowlisting.py
googleads_housekeeper/domain/commands.py
googleads_housekeeper/domain/events.py
googleads_housekeeper/domain/execution.py
googleads_housekeeper/domain/placements.py
googleads_housekeeper/domain/settings.py
googleads_housekeeper/domain/task.py
googleads_housekeeper/services/__init__.py
googleads_housekeeper/services/enums.py
googleads_housekeeper/services/exclusion_service.py
googleads_housekeeper/services/exclusion_specification.py
googleads_housekeeper/services/handlers.py
googleads_housekeeper/services/messagebus.py
googleads_housekeeper/services/rules_parser.py
googleads_housekeeper/services/unit_of_work.py
googleads_housekeeper/services/external_parsers/__init__.py
googleads_housekeeper/services/external_parsers/base_parser.py
googleads_housekeeper/services/external_parsers/website_parser.py
googleads_housekeeper/services/external_parsers/youtube_data_parser.py
tests/__init__.py
tests/conftest.py
tests/test_exclusion_specification.py
tests/test_external_parsers.py
tests/test_handlers.py
tests/test_placements.py
tests/test_rules_parser.py