Metadata-Version: 2.1
Name: google-ads-house-keeper
Version: 0.0.42
Author: Google Inc. (gTech gPS CSE team)
Author-email: no-reply@google.com
License: Apache 2.0
Requires-Python: >3.8
Provides-Extra: full
Provides-Extra: gcp
